coltrane/__init__.py
coltrane/config/__init__.py
coltrane/config/cache.py
coltrane/config/paths.py
coltrane/config/settings.py
coltrane/console.py
coltrane/feeds.py
coltrane/management/__init__.py
coltrane/management/commands/__init__.py
coltrane/management/commands/build.py
coltrane/manifest.py
coltrane/renderer.py
coltrane/retriever.py
coltrane/sitemaps.py
coltrane/templates/coltrane/base.html
coltrane/templates/coltrane/content.html
coltrane/templatetags/__init__.py
coltrane/templatetags/coltrane_tags.py
coltrane/urls.py
coltrane/utils.py
coltrane/views.py
coltrane_web-0.18.2.dist-info/entry_points.txt
coltrane_web-0.18.2.dist-info/LICENSE
coltrane_web-0.18.2.dist-info/WHEEL
coltrane_web-0.18.2.dist-info/METADATA
coltrane_web-0.18.2.dist-info/RECORD
