Metadata-Version: 2.1
Name: coltrane-web
Version: 0.18.2
Summary: A simple content site framework that harnesses the power of Django without the hassle.
Home-page: https://github.com/adamghill/coltrane/
License: MIT
Keywords: django,python,static,markdown
Author: adamghill
Author-email: adam@adamghill.com
Requires-Python: >=3.7,<4.0
Classifier: License :: OSI Approved :: MIT License
Classifier: Programming Language :: Python :: 3
Classifier: Programming Language :: Python :: 3.10
Classifier: Programming Language :: Python :: 3.7
Classifier: Programming Language :: Python :: 3.8
Classifier: Programming Language :: Python :: 3.9
Provides-Extra: deploy
Provides-Extra: docs
Requires-Dist: Django (>3.0)
Requires-Dist: Sphinx (>=4.3.2,<5.0.0); extra == "docs"
Requires-Dist: click (>=8.0.0,<9.0.0)
Requires-Dist: dateparser (>=1.1.0,<2.0.0)
Requires-Dist: django-browser-reload (>=1.3.0,<2.0.0)
Requires-Dist: django-fastdev (>=1.3.0,<2.0.0)
Requires-Dist: furo (>=2021.11.23,<2022.0.0); extra == "docs"
Requires-Dist: gunicorn (>=20.1.0,<21.0.0); extra == "deploy"
Requires-Dist: halo (>=0.0.31,<0.0.32)
Requires-Dist: linkify-it-py (>=1.0.3,<2.0.0); extra == "docs"
Requires-Dist: markdown2 (>=2.4.2,<3.0.0)
Requires-Dist: myst-parser (>=0.16.1,<0.17.0); extra == "docs"
Requires-Dist: python-dotenv (>0.17)
Requires-Dist: rich-click (>=0.2.0,<0.3.0)
Requires-Dist: sphinx-autobuild (>=2021.3.14,<2022.0.0); extra == "docs"
Requires-Dist: sphinx-copybutton (>=0.4.0,<0.5.0); extra == "docs"
Requires-Dist: toml; extra == "docs"
Requires-Dist: whitenoise (>=5.3.0,<6.0.0); extra == "deploy"
Project-URL: Documentation, https://coltrane.readthedocs.io/
Project-URL: Funding, https://github.com/sponsors/adamghill
Project-URL: Repository, https://github.com/adamghill/coltrane/
